mwdb_iocextract/__init__.py
mwdb_iocextract/api.py
mwdb_iocextract/errors.py
mwdb_iocextract/model.py
mwdb_iocextract/modules.py
mwdb_iocextract/run.py
mwdb_iocextract/test_misp.py
mwdb_iocextract-1.2.2.data/data/requirements.txt/requirements.txt
mwdb_iocextract-1.2.2.dist-info/METADATA
mwdb_iocextract-1.2.2.dist-info/WHEEL
mwdb_iocextract-1.2.2.dist-info/top_level.txt
mwdb_iocextract-1.2.2.dist-info/RECORD
