Metadata-Version: 2.1
Name: mwdb-iocextract
Version: 1.2.2
Summary: Mwdb config parser
Home-page: UNKNOWN
Author: CERT Polska
Author-email: info@cert.pl
License: UNKNOWN
Platform: UNKNOWN
Classifier: Programming Language :: Python
Classifier: License :: OSI Approved :: MIT License
Classifier: Operating System :: OS Independent
Requires-Dist: malduck
Requires-Dist: mwdblib (>=3.3.0)
Requires-Dist: pycryptodomex
Requires-Dist: pymisp
